<break time="1.0s"/> 能否跟上車最後去哪裡?<break time='0.2s'/><break time="0.1s"/>shortbreak能否shortbreakCan or not<break time="0.1s"/><break time="0.1s"/>shortbreak跟上車shortbreakGet in the car<break time="0.1s"/><break time="0.1s"/>shortbreak最後shortbreakIn the end / Finally<break time="0.1s"/><break time='0.2s'/> 能否跟上車最後去哪裡?<break time='0.2s'/><break time="0.1s"/>shortbreak去哪裡shortbreakGo where<break time="0.1s"/><break time='0.2s'/> 能否跟上車最後去哪裡?<break time='0.2s'/><break time='0.2s'/> 能否跟上車最後去哪裡?<break time='0.2s'/> 我們看了很多馬路的監控視頻<break time='0.2s'/><break time="0.1s"/>shortbreak我們shortbreakwe<break time="0.1s"/><break time="0.1s"/>shortbreak看了shortbreakwatched<break time="0.1s"/><break time="0.1s"/>shortbreak很多shortbreakmany<break time="0.1s"/><break time='0.2s'/> 我們看了很多馬路的監控視頻<break time='0.2s'/><break time="0.1s"/>shortbreak馬路shortbreakroad/street<break time="0.1s"/><break time="0.1s"/>shortbreak監控視頻shortbreaksurveillance videos<break time="0.1s"/><break time="0.1s"/>shortbreak我們看了shortbreakwe watched<break time="0.1s"/><break time='0.2s'/> 我們看了很多馬路的監控視頻<break time='0.2s'/><break time="0.1s"/>shortbreak很多馬路shortbreakmany streets<break time="0.1s"/><break time="0.1s"/>shortbreak的監控視頻shortbreakof surveillance videos<break time="0.1s"/><break time="0.1s"/>shortbreak馬路的監控視頻shortbreaksurveillance videos of the street<break time="0.1s"/><break time='0.2s'/> 我們看了很多馬路的監控視頻<break time='0.2s'/><break time='0.2s'/> 我們看了很多馬路的監控視頻<break time='0.2s'/><break time='0.2s'/> 我們看了很多馬路的監控視頻<break time='0.2s'/> 發現這部車最後在臨近公路出現過<break time='0.2s'/><break time="0.1s"/>shortbreak發現shortbreakto discover; to find out<break time="0.1s"/><break time="0.1s"/>shortbreak這部車shortbreakthis car<break time="0.1s"/><break time="0.1s"/>shortbreak在shortbreakat; in; on<break time="0.1s"/><break time='0.2s'/> 發現這部車最後在臨近公路出現過<break time='0.2s'/><break time="0.1s"/>shortbreak臨近shortbreaknear; close to<break time="0.1s"/><break time="0.1s"/>shortbreak公路shortbreakhighway; road<break time="0.1s"/><break time="0.1s"/>shortbreak出現過shortbreakhas appeared; was seen<break time="0.1s"/><break time='0.2s'/> 發現這部車最後在臨近公路出現過<break time='0.2s'/><break time='0.2s'/> 發現這部車最後在臨近公路出現過<break time='0.2s'/><break time='0.2s'/> 發現這部車最後在臨近公路出現過<break time='0.2s'/> 阿正, 找人魚腦出一下<break time='0.2s'/><break time="0.1s"/>shortbreak阿正shortbreakA-Zheng (a person's name)<break time="0.1s"/><break time="0.1s"/>shortbreak找人shortbreakto look for someone<break time="0.1s"/><break time="0.1s"/>shortbreak魚腦shortbreakfish brain (often used to refer to someone who is forgetful or not very smart)<break time="0.1s"/><break time='0.2s'/> 阿正, 找人魚腦出一下<break time='0.2s'/><break time="0.1s"/>shortbreak出一下shortbreakto come out for a moment<break time="0.1s"/><break time='0.2s'/> 阿正, 找人魚腦出一下<break time='0.2s'/><break time='0.2s'/> 阿正, 找人魚腦出一下<break time='0.2s'/> 看看能否找到這部車 最後我去交通部<break time='0.2s'/><break time="0.1s"/>shortbreak看看shortbreaktake a look<break time="0.1s"/><break time="0.1s"/>shortbreak找到shortbreakfind<break time="0.1s"/><break time="0.1s"/>shortbreak我去shortbreakI go<break time="0.1s"/><break time='0.2s'/> 看看能否找到這部車 最後我去交通部<break time='0.2s'/><break time="0.1s"/>shortbreak交通部shortbreakDepartment of Transportation<break time="0.1s"/><break time='0.2s'/> 看看能否找到這部車 最後我去交通部<break time='0.2s'/><break time='0.2s'/> 看看能否找到這部車 最後我去交通部<break time='0.2s'/> 拿了臨近公路的閉路電視回來看<break time='0.2s'/><break time="0.1s"/>shortbreak拿了shortbreaktook<break time="0.1s"/><break time="0.1s"/>shortbreak閉路電視shortbreakCCTV<break time="0.1s"/><break time="0.1s"/>shortbreak回來shortbreakcame back<break time="0.1s"/><break time='0.2s'/> 拿了臨近公路的閉路電視回來看<break time='0.2s'/><break time="0.1s"/>shortbreak回來看shortbreakcame back to watch<break time="0.1s"/><break time="0.1s"/>shortbreak臨近公路shortbreaknearby road<break time="0.1s"/><break time="0.1s"/>shortbreak臨近公路的閉路電視shortbreakCCTV near the road<break time="0.1s"/><break time='0.2s'/> 拿了臨近公路的閉路電視回來看<break time='0.2s'/><break time='0.2s'/> 拿了臨近公路的閉路電視回來看<break time='0.2s'/><break time='0.2s'/> 拿了臨近公路的閉路電視回來看<break time='0.2s'/> 石東, 我幫你的電話解鎖了<break time='0.2s'/><break time="0.1s"/>shortbreak石東shortbreakShi Dong (a name)<break time="0.1s"/><break time="0.1s"/>shortbreak我幫你shortbreakI helped you<break time="0.1s"/><break time="0.1s"/>shortbreak解鎖shortbreakunlock<break time="0.1s"/><break time='0.2s'/> 石東, 我幫你的電話解鎖了<break time='0.2s'/><break time='0.2s'/> 石東, 我幫你的電話解鎖了<break time='0.2s'/><break time='0.2s'/> 石東, 我幫你的電話解鎖了<break time='0.2s'/> 之後有什麼發現? 報告出事當晚 有個電話打給他五次 對方已經用了太空卡<break time='0.2s'/><break time="0.1s"/>shortbreak之後有什麼發現shortbreakWhat was discovered afterwards?<break time="0.1s"/><break time="0.1s"/>shortbreak報告出事當晚shortbreakReport on the night of the incident<break time="0.1s"/><break time="0.1s"/>shortbreak有個電話打給他shortbreakThere was a phone call to him<break time="0.1s"/><break time='0.2s'/> 之後有什麼發現? 報告出事當晚 有個電話打給他五次 對方已經用了太空卡<break time='0.2s'/><break time="0.1s"/>shortbreak打給他五次shortbreakCalled him five times<break time="0.1s"/><break time="0.1s"/>shortbreak對方已經用了太空卡shortbreakThe other party has already used a burn phone (prepaid SIM card)<break time="0.1s"/><break time='0.2s'/> 之後有什麼發現? 報告出事當晚 有個電話打給他五次 對方已經用了太空卡<break time='0.2s'/><break time='0.2s'/> 之後有什麼發現? 報告出事當晚 有個電話打給他五次 對方已經用了太空卡<break time='0.2s'/> 所以查不到機主是什麼人<break time='0.2s'/><break time="0.1s"/>shortbreak查不到shortbreakcan't find / can't look up<break time="0.1s"/><break time="0.1s"/>shortbreak機主shortbreakthe owner of the phone / the subscriber<break time="0.1s"/><break time="0.1s"/>shortbreak是什麼人shortbreakis who / is what kind of person<break time="0.1s"/><break time='0.2s'/> 所以查不到機主是什麼人<break time='0.2s'/><break time='0.2s'/> 所以查不到機主是什麼人<break time='0.2s'/><break time='0.2s'/> 所以查不到機主是什麼人<break time='0.2s'/> 用這部手機打給波哥 很有可能是叫他拿出賀卡印出來的人<break time='0.2s'/><break time="0.1s"/>shortbreak用這部手機shortbreakuse this mobile phone<break time="0.1s"/><break time="0.1s"/>shortbreak打給shortbreakcall (someone)<break time="0.1s"/><break time="0.1s"/>shortbreak波哥shortbreakBrother Po (a nickname)<break time="0.1s"/><break time='0.2s'/> 用這部手機打給波哥 很有可能是叫他拿出賀卡印出來的人<break time='0.2s'/><break time="0.1s"/>shortbreak很ossa有可能shortbreakvery likely<break time="0.1s"/><break time="0.1s"/>shortbreak叫他shortbreakask him to<break time="0.1s"/><break time="0.1s"/>shortbreak拿出shortbreaktake out<break time="0.1s"/><break time='0.2s'/> 用這部手機打給波哥 很有可能是叫他拿出賀卡印出來的人<break time='0.2s'/><break time="0.1s"/>shortbreak賀卡shortbreakgreeting card<break time="0.1s"/><break time="0.1s"/>shortbreak印出來shortbreakprint out<break time="0.1s"/><break time='0.2s'/> 用這部手機打給波哥 很有可能是叫他拿出賀卡印出來的人<break time='0.2s'/><break time='0.2s'/> 用這部手機打給波哥 很有可能是叫他拿出賀卡印出來的人<break time='0.2s'/> 阿龍, 阿龍 《 天下之旅》<break time='0.2s'/><break time="0.1s"/>shortbreak阿龍shortbreakAh Lung (a common Cantonese name)<break time="0.1s"/><break time="0.1s"/>shortbreak《天下之旅》shortbreakJourney Around the World<break time="0.1s"/><break time='0.2s'/> 阿龍, 阿龍 《 天下之旅》<break time='0.2s'/><break time='0.2s'/> 阿龍, 阿龍 《 天下之旅》<break time='0.2s'/> <break time="1.0s"/>